[
    {
        "id": "20250520051112",
        "date": "20/05/2025 05:11",
        "username": "admin",
        "customer": {
            "name": "Anam",
            "phone": "a",
            "address": "a"
        },
        "items": [
            {
                "id": 1,
                "name": "Bawang Merah",
                "price": 37905,
                "quantity": 1
            }
        ],
        "total": 52905,
        "payment": {
            "method": "Transfer BRI",
            "status": "pending"
        },
        "shipping": {
            "method": "JNE",
            "cost": 15000,
            "estimate": "2-3 hari"
        },
        "status": "pending"
    },
    {
        "id": "20250520052838",
        "date": "20/05/2025 05:28",
        "username": "admin",
        "customer": {
            "name": "a",
            "phone": "a",
            "address": "a"
        },
        "items": [
            {
                "id": 1,
                "name": "Bawang Merah",
                "price": 37905,
                "quantity": 10
            }
        ],
        "total": 394050,
        "payment": {
            "method": "Transfer BRI",
            "status": "pending"
        },
        "shipping": {
            "method": "JNE",
            "cost": 15000,
            "estimate": "2-3 hari"
        },
        "status": "pending"
    },
    {
        "id": "20250524205837",
        "date": "24/05/2025 20:58",
        "username": "admin",
        "customer": {
            "name": "A",
            "phone": "A",
            "address": "A"
        },
        "items": [
            {
                "id": 1,
                "name": "Bawang Merah",
                "price": 37905,
                "quantity": 4
            }
        ],
        "total": 166620,
        "payment": {
            "method": "Transfer BRI",
            "status": "pending"
        },
        "shipping": {
            "method": "JNE",
            "cost": 15000,
            "estimate": "2-3 hari"
        },
        "status": "pending"
    },
    {
        "id": "20250524210545",
        "date": "24/05/2025 21:05",
        "username": "admin",
        "customer": {
            "name": "d",
            "phone": "d",
            "address": "d"
        },
        "items": [
            {
                "id": 1,
                "name": "Bawang Merah",
                "price": 37905,
                "quantity": 2
            }
        ],
        "total": 90810,
        "payment": {
            "method": "Transfer BRI",
            "status": "pending"
        },
        "shipping": {
            "method": "JNE",
            "cost": 15000,
            "estimate": "2-3 hari"
        },
        "status": "pending"
    },
    {
        "id": "20250524211832",
        "date": "24/05/2025 21:18",
        "username": "admin",
        "customer": {
            "name": "as",
            "phone": "as",
            "address": "as"
        },
        "items": [
            {
                "id": 1,
                "name": "Bawang Merah",
                "price": 37905,
                "quantity": 1
            }
        ],
        "total": 52905,
        "payment": {
            "method": "Transfer BRI",
            "status": "pending"
        },
        "shipping": {
            "method": "JNE",
            "cost": 15000,
            "estimate": "2-3 hari"
        },
        "status": "pending"
    },
    {
        "id": "20250524212857",
        "date": "24/05/2025 21:28",
        "username": "admin",
        "customer": {
            "name": "a",
            "phone": "a",
            "address": "a"
        },
        "items": [
            {
                "id": 1,
                "name": "Bawang Merah",
                "price": 37905,
                "quantity": 1
            }
        ],
        "total": 52905,
        "payment": {
            "method": "Transfer SeaBank",
            "status": "pending"
        },
        "shipping": {
            "method": "JNE",
            "cost": 15000,
            "estimate": "2-3 hari"
        },
        "status": "pending"
    }
]